[
  {
    "full_name": "rust-lang/rustfmt",
    "stargazers_count": 3590,
    "open_issues_count": 375,
    "forks_count": 576
  },
  {
    "full_name": "rust-lang/rustfmt",
    "stargazers_count": 3590,
    "open_issues_count": 375,
    "forks_count": 576
  },
  {
    "full_name": "rust-lang/rustfmt",
    "stargazers_count": 3590,
    "open_issues_count": 375,
    "forks_count": 576
  },
  {
    "full_name": "open-sauced/open-sauced",
    "stargazers_count": 399,
    "open_issues_count": 36,
    "forks_count": 113
  }
]